MANIFEST.in
README.txt
setup.py
docs/HISTORY.txt
docs/INSTALL.txt
docs/LICENSE.GPL
docs/LICENSE.txt
docs/TODO.txt
uwosh/__init__.py
uwosh.ATImageEditor.egg-info/PKG-INFO
uwosh.ATImageEditor.egg-info/SOURCES.txt
uwosh.ATImageEditor.egg-info/dependency_links.txt
uwosh.ATImageEditor.egg-info/entry_points.txt
uwosh.ATImageEditor.egg-info/namespace_packages.txt
uwosh.ATImageEditor.egg-info/not-zip-safe
uwosh.ATImageEditor.egg-info/requires.txt
uwosh.ATImageEditor.egg-info/top_level.txt
uwosh/ATImageEditor/__init__.py
uwosh/ATImageEditor/configure.zcml
uwosh/ATImageEditor/profiles.zcml
uwosh/ATImageEditor/tests.py
uwosh/ATImageEditor/version.txt
uwosh/ATImageEditor/browser/__init__.py
uwosh/ATImageEditor/browser/commands.py
uwosh/ATImageEditor/browser/configure.zcml
uwosh/ATImageEditor/browser/css.zcml
uwosh/ATImageEditor/browser/imageeditor.kss
uwosh/ATImageEditor/browser/imageeditor.pt
uwosh/ATImageEditor/browser/imageeditor.py
uwosh/ATImageEditor/browser/imageeditorPlugins.js
uwosh/ATImageEditor/browser/js.zcml
uwosh/ATImageEditor/browser/kss.zcml
uwosh/ATImageEditor/browser/resources/imageeditor.js
uwosh/ATImageEditor/browser/resources/jquery-ui-personalized-1.6b.min.js
uwosh/ATImageEditor/browser/resources/style.css
uwosh/ATImageEditor/browser/resources/icons/apply.png
uwosh/ATImageEditor/browser/resources/icons/edit-redo.png
uwosh/ATImageEditor/browser/resources/icons/edit-undo.png
uwosh/ATImageEditor/browser/resources/icons/process-stop.png
uwosh/ATImageEditor/browser/resources/icons/stock-resize-16.png
uwosh/ATImageEditor/browser/resources/icons/stock-rotate-270-16.png
uwosh/ATImageEditor/browser/resources/icons/stock-rotate-90-16.png
uwosh/ATImageEditor/browser/resources/icons/stock-selection-intersect-16.png
uwosh/ATImageEditor/browser/resources/icons/stock-template-16.png
uwosh/ATImageEditor/browser/resources/icons/stock-tool-blur-16.png
uwosh/ATImageEditor/browser/resources/icons/stock-tool-brightness-16.png
uwosh/ATImageEditor/browser/resources/icons/stock-tool-colorize-16.png
uwosh/ATImageEditor/browser/resources/icons/stock-tool-contrast-16.png
uwosh/ATImageEditor/browser/resources/icons/stock-tool-flip-16.png
uwosh/ATImageEditor/browser/resources/icons/stock-tool-rotate-16.png
uwosh/ATImageEditor/browser/resources/imgareaselect-0.4.2/GPL-LICENSE.txt
