Metadata-Version: 1.0
Name: uwosh.ATImageEditor
Version: 0.3.2
Summary: release just so you can uninstall the bloody thing from your plone site!
Home-page: http://plone.org/products/atimageeditor
Author: Nathan Van Gheem
Author-email: vangheem@gmail.com
License: GPL
Keywords: atimage image resize scrop rotate
Platform: UNKNOWN
Classifier: Framework :: Plone
Classifier: Programming Language :: Python
Classifier: Topic :: Software Development :: Libraries :: Python Modules
